{
  "fallback": "empty",
  "elements": [
    {
      "weight": 100,
      "element": {
        "element_type": "minecraft:single_pool_element",
        "projection": "rigid",
        "location": "qwuthal:dungeon/air",
        "processors": "empty"
      }
    },
    {
      "weight": 45,
      "element": {
        "element_type": "minecraft:single_pool_element",
        "projection": "rigid",
        "location": "qwuthal:dungeon/generic_loot",
        "processors": "empty"
      }
    },
    {
      "weight": 20,
      "element": {
        "element_type": "minecraft:single_pool_element",
        "projection": "rigid",
        "location": "qwuthal:dungeon/jackpot",
        "processors": "empty"
      }
    }
  ]
}
